modact/__init__.py
modact/actuator.py
modact/materials.py
modact/meshutils.py
modact/problems.py
modact/util.py
modact/interfaces/__init__.py
modact/interfaces/pymoo.py
modact/models/__init__.py
modact/models/base.py
modact/models/gears.py
modact/models/motors.py
modact-1.0.1.dist-info/licenses/LICENSE
modact-1.0.1.dist-info/METADATA
modact-1.0.1.dist-info/WHEEL
modact-1.0.1.dist-info/top_level.txt
modact-1.0.1.dist-info/RECORD
