Metadata-Version: 2.4
Name: modact
Version: 1.0.1
Summary: Multi-Objective Design of Actuators
Author-email: Cyril Picard <cyrilp@mit.edu>
Project-URL: Bug Reports, https://github.com/epfl-lamd/modact/issues
Project-URL: Source, https://github.com/epfl-lamd/modact/
Project-URL: Home, https://github.com/epfl-lamd/modact/
Classifier: Intended Audience :: Science/Research
Classifier: Topic :: Scientific/Engineering
Classifier: Programming Language :: Python :: 3.8
Classifier: Programming Language :: Python :: 3.9
Classifier: Programming Language :: Python :: 3.10
Classifier: Programming Language :: Python :: 3.11
Classifier: Programming Language :: Python :: 3.12
Requires-Python: >=3.8
License-File: LICENSE
Requires-Dist: attrs
Requires-Dist: cached_property>=1.5.1
Requires-Dist: networkx
Requires-Dist: numpy
Requires-Dist: python-fcl
Requires-Dist: scipy
Requires-Dist: trimesh
Dynamic: license-file
